thorlabs_apt_protocol/__init__.py
thorlabs_apt_protocol/functions.py
thorlabs_apt_protocol/parsing.py
thorlabs_apt_protocol/unpacker.py
thorlabs_apt_protocol-29.0.0.dist-info/LICENSE
thorlabs_apt_protocol-29.0.0.dist-info/WHEEL
thorlabs_apt_protocol-29.0.0.dist-info/METADATA
thorlabs_apt_protocol-29.0.0.dist-info/RECORD
