Metadata-Version: 2.1
Name: thorlabs-apt-protocol
Version: 29.0.0
Summary: Functional implementation of the thorlabs APT protocol
Home-page: https://gitlab.com/yaq/thorlabs-apt-protocol
Author: Kyle Sunden
Author-email: contact@ksunden.space
Requires-Python: >=3.6
Classifier: Development Status :: 2 - Pre-Alpha
Classifier: Intended Audience :: Science/Research
Classifier: License :: OSI Approved :: MIT License
Classifier: Natural Language :: English
Classifier: Programming Language :: Python :: 3
Classifier: Programming Language :: Python :: 3.6
Classifier: Programming Language :: Python :: 3.7
Classifier: Programming Language :: Python :: 3.8
Classifier: Topic :: Scientific/Engineering
Requires-Dist: black ; extra == "dev"
Requires-Dist: pre-commit ; extra == "dev"
Project-URL: Issues, https://gitlab.com/yaq/thorlabs-apt-protocol/issues
Project-URL: Source, https://gitlab.com/yaq/thorlabs-apt-protocol
Provides-Extra: dev
